<?xml version="1.0" encoding="UTF-8"?>
<benefit id="1861">
      <name>Salon Ariana</name>
      <cardType>ISIC</cardType>
      <cardType>ITIC</cardType>
      <cardType>IYTC</cardType>
      <cardType>SCHOLAR</cardType>
      <address>Gorazdova 14, Praha 2</address>
      <phone>224 915 202, 603 431 900</phone>
      <email>ariana@salonariana.cz</email>
      <web>www.salonariana.cz</web>
      <info>Masáže - sleva 20 % klasická masáž (relaxační, sportovní) - sleva 10 % na všechny ostatní masáže Kadeřnictví - sleva 20 % komplet střih - sleva 10 % střih + barva, přeliv, melírování vlasů Pedikura - sleva 20 % pedikérské ošetření KLASIK - sleva 10 % pedikérské ošetření SPECIAL Manikura - sleva 20 % základní úprava - sleva 10 % modeláž nehtů UV gelem Kosmetika - sleva 10 % kompletní ošetření pleti Solarium - sleva 10 % 1 min bez permanentky - sleva 20 % na permanentku (100 min) AKCE SALONU 3 SLUŽBY V 1 DEN sleva 25 % (cena po slevě je 1500,-Kč) - barva vlasů + střih - masáž nebo kosmetika - manikura nebo pedikura</info>
   <latitude>50.0744897</latitude>
   <longitude>14.4150327</longitude>
</benefit>
