<?xml version="1.0" encoding="UTF-8"?>
<benefit id="1537">
      <name>Moje psychologie - časopis</name>
      <cardType>ISIC</cardType>
      <cardType>ITIC</cardType>
      <cardType>IYTC</cardType>
      <cardType>SCHOLAR</cardType>
      <address>Mezi Vodami 1952/9, Praha 4</address>
      <phone>800 300 302</phone>
      <email>predplatne.mf@cpost.cz</email>
      <web>www.mf.cz/produkty/moje-psychologie</web>
      <info>sleva 20 % na roční předplatné za 552 Kč (plná cena 690 Kč)</info>
   <latitude>50.0079448</latitude>
   <longitude>14.4026010</longitude>
</benefit>
