<?xml version="1.0" encoding="UTF-8"?>
<benefit id="1854">
      <name>Pace Jeans</name>
      <cardType>ISIC</cardType>
      <cardType>ITIC</cardType>
      <cardType>IYTC</cardType>
      <cardType>SCHOLAR</cardType>
      <address>Džíny &amp; Mantl, Americká 49, Plzeň</address>
      <phone>377 329 436</phone>
      <email>info@pacejeans.cz</email>
      <web>www.pacejeans.cz</web>
      <info>sleva 10 % na veškerý sortiment nevztahuje se na již zlevněné zboží</info>
   <latitude></latitude>
   <longitude></longitude>
</benefit>
