<?xml version="1.0" encoding="UTF-8"?>
<benefit id="273">
      <name>Památník Jaroslava Ježka</name>
      <cardType>ISIC</cardType>
      <cardType>ITIC</cardType>
      <address>Kaprova 10, Praha 1</address>
      <phone>257 257 739</phone>
      <email>marketa_kabelkova@nm.cz</email>
      <web>www.nm.cz</web>
      <info>Snížená cena vstupného pro držitele karet. Běžná cena 20 Kč, cena po slevě 10 Kč.</info>
   <latitude>50.0882061</latitude>
   <longitude>14.4176902</longitude>
</benefit>
