<?xml version="1.0" encoding="UTF-8"?>
<benefit id="777">
      <name>Twilight Breaking Dawn Afterparty</name>
      <cardType>ISIC</cardType>
      <cardType>ITIC</cardType>
      <cardType>IYTC</cardType>
      <cardType>SCHOLAR</cardType>
      <address>GoraZdova 14, Praha</address>
      <phone>724 839 238</phone>
      <email>info@ktsproduction.cz</email>
      <web>www.ktsproduction.cz</web>
      <info>10% sleva na vstup na Twilight Breaking Dawn Afterparty v předprodeji v sítích Ticketstream a na místě ve dni konání</info>
   <latitude>50.0744897</latitude>
   <longitude>14.4150327</longitude>
</benefit>
