<?xml version="1.0" encoding="UTF-8"?>
<benefit id="1479">
      <name>Velosport HB</name>
      <cardType>ISIC</cardType>
      <cardType>ITIC</cardType>
      <cardType>IYTC</cardType>
      <cardType>SCHOLAR</cardType>
      <address>Benešova 14, Jihlava</address>
      <phone>567 301 296</phone>
      <email>hblazek@cbox.xz</email>
      <web/>
      <info>sleva 10% na nezlevněná kola a ostatní zboží sleva 5% na zlevněná kola</info>
   <latitude>49.3961997</latitude>
   <longitude>15.5880257</longitude>
</benefit>
