<?xml version="1.0" encoding="UTF-8"?>
<benefit id="456">
      <name>McDonald's</name>
      <cardType>ISIC</cardType>
      <cardType>SCHOLAR</cardType>
      <address>Shopping Park Ikea, Skandinávská 2,, Brno</address>
      <phone/>
      <email/>
      <web>www.mcdonalds.cz</web>
      <info>Denní nabídka: Big Mac a nebo McChicken a střední hranolky za 79 Kč   Ranní nabídka: McMuffin se slaninou a Cappuccino za 49 Kč  </info>
   <latitude>49.1575366</latitude>
   <longitude>16.6276810</longitude>
</benefit>
