<?xml version="1.0" encoding="UTF-8"?>
<benefit id="1367">
      <name>Galaxy – AVS přístroj / psychowalkam</name>
      <cardType>ISIC</cardType>
      <cardType>ITIC</cardType>
      <cardType>IYTC</cardType>
      <cardType>SCHOLAR</cardType>
      <address>5. května 61, Liberec</address>
      <phone>485 172 377, 731 028 716</phone>
      <email>liberec@galaxy.cz</email>
      <web>www.galaxy.cz, www.magicka.cz</web>
      <info>10% na veškeré produkty. AVS přístroj Psychowalkman Seznam pozitivních účinků při užívání AVS přístrojů Relaxace a meditace Stres a deprese Učení a koncetrace Bolest a migréna Potíže se spánkem a únava Mentální vitalita a odolnost</info>
   <latitude>50.7716015</latitude>
   <longitude>15.0631633</longitude>
</benefit>
