<?xml version="1.0" encoding="UTF-8"?>
<benefit id="412">
      <name>ixi club</name>
      <cardType>ISIC</cardType>
      <cardType>SCHOLAR</cardType>
      <address>Kunětická 133, Pardubice</address>
      <phone>466411991-2</phone>
      <email/>
      <web>www.ixiclub.cz</web>
      <info>Squash (po-pá: 7-15h - 150 Kč, 15 - 22h - 200Kč, 22 - 23h 175Kč), Bowling (po-pá: 7-15h 170 Kč, 15 - 23h 220Kč), Trampolíny (1 vstup = 65 Kč. Permanetka 10h 600Kč, 20h 11000 Kč). Nárok na slevu je uznán pouze v případě, že všichni sportující předloží platný průkaz ISIC (SCHOLAR)</info>
   <latitude>50.0533709</latitude>
   <longitude>15.7708807</longitude>
</benefit>
